{
  "metadata": {
    "name": "Design Resources for Developers",
    "version": "1.0.0",
    "lastUpdated": "2024-12-10",
    "totalResources": 373,
    "totalCategories": 35
  },
  "categories": [
    {
      "id": 1,
      "name": "UI Graphics",
      "slug": "ui-graphics",
      "description": "Websites and resources for UI graphics, illustrations, patterns, and backgrounds",
      "resources": [
        {"name": "SVG Sine Waves", "url": "https://www.sinwaver.com/", "description": "Export perfect sine waves as SVG for your front-end projects"},
        {"name": "UI Design Daily", "url": "https://uidesigndaily.com/", "description": "Awesome UI Components of all types"},
        {"name": "100 Daily UI", "url": "https://100dailyui.webflow.io/", "description": "Free Figma library of products, elements, and screens"},
        {"name": "Sketch App Sources", "url": "https://www.sketchappsources.com/", "description": "Sketch UIs, wireframes, icons and much more"},
        {"name": "Humaaans", "url": "https://www.humaaans.com/", "description": "Cool illustrations of people with the ability to mix and match"},
        {"name": "Paaatterns", "url": "https://products.ls.graphics/paaatterns/", "description": "Free collection of beautiful patterns for all vector formats"},
        {"name": "Absurd Design", "url": "https://absurd.design/", "description": "Free surrealist illustrations for designers and developers"},
        {"name": "unDraw", "url": "https://undraw.co/", "description": "Open-source illustrations for any idea you can imagine and create"},
        {"name": "ManyPixels", "url": "https://www.manypixels.co/gallery/", "description": "Monochromatic, Isometric high-quality illustrations"},
        {"name": "Open Peeps", "url": "https://www.openpeeps.com/", "description": "Hand drawn illustration library"},
        {"name": "InVision Design Resources", "url": "https://www.invisionapp.com/inside-design/design-resources/", "description": "Library of free, high-quality UI kits, icon packs, and mockups"},
        {"name": "Open Doodles", "url": "https://www.opendoodles.com/", "description": "A Free Set of Sketchy Illustrations"},
        {"name": "Blush", "url": "https://blush.design/", "description": "Free customizable illustrations with Figma Plugin"},
        {"name": "Hero Patterns", "url": "http://www.heropatterns.com/", "description": "A collection of repeatable SVG background patterns"},
        {"name": "BEAUBUS Patterns", "url": "https://patterns.beaubus.com/", "description": "A set of 150+ free SVG patterns and backgrounds"},
        {"name": "IRA Design", "url": "https://iradesign.io/", "description": "An open-source gradient illustrations collection by creative tim"},
        {"name": "Transparent Textures", "url": "https://www.transparenttextures.com/", "description": "A collection of transparent textures background patterns"},
        {"name": "Icons8 Illustrations", "url": "https://icons8.com/illustrations", "description": "Vector illustrations to class up your project"},
        {"name": "Patternico", "url": "https://patternico.com", "description": "Seamless Pattern Maker"},
        {"name": "Pixeltrue Illustrations", "url": "https://www.pixeltrue.com/illustrations", "description": "Free Animated Illustrations"},
        {"name": "Abstract User Avatar API", "url": "https://www.abstractapi.com/user-avatar-api", "description": "API to create simple yet flexible user avatars from user names or emails"},
        {"name": "Sketchvalley", "url": "https://sketchvalley.com/", "description": "Download free PNG, SVG or AI file"},
        {"name": "PatternPad", "url": "https://patternpad.com/", "description": "Free and unlimited unique pattern designs"},
        {"name": "Dimensions", "url": "https://www.dimensions.com/", "description": "Reference database documenting standard measurements of everyday objects and spaces"},
        {"name": "Freebiesbug", "url": "https://freebiesbug.com/", "description": "Hand-picked resources for web designers and developers, constantly updated"},
        {"name": "Flexiple", "url": "https://2.flexiple.com/scale/all-illustrations", "description": "One new high-quality, open-source illustration each day"},
        {"name": "Cool Text", "url": "https://cooltext.com/", "description": "FREE graphics generator for web pages and anywhere else you need an impressive logo"},
        {"name": "Illustration Kit", "url": "https://illustrationkit.com/", "description": "Premium open source illustrations added daily"},
        {"name": "Doodad Pattern Generator", "url": "https://doodad.dev/pattern-generator/", "description": "Create unique, seamless, royalty-free patterns"},
        {"name": "Pattern Monster", "url": "https://pattern.monster/", "description": "A simple online pattern generator to create repeatable SVG patterns"},
        {"name": "Exemplar", "url": "https://themeselection.com/products/exemplar-free-avatar-library-for-figma-and-sketch/", "description": "Free Avatar Library for Figma and Sketch"},
        {"name": "UIBundle", "url": "https://uibundle.com", "description": "Thousands of Free Design Resources like UI Kits, Mockups, Illustrations, Icons, Fonts, 3D assets, Templates and more"},
        {"name": "Openby.design", "url": "http://openby.design/", "description": "Custom crafted free UI design resources, for personal and commercial projects"},
        {"name": "Design Stripe", "url": "https://designstripe.com/", "description": "Create beautiful illustrations, no design skills needed"},
        {"name": "HOLA SVG!", "url": "https://holasvg.com/", "description": "An SVG playground to share SVG stuff"},
        {"name": "Symu.co", "url": "https://symu.co/freebies/templates-4/", "description": "Free templates, UI kits, icon, PSD"},
        {"name": "Mesh Gradient", "url": "https://meshgradient.in/", "description": "Generate & download beautiful mesh gradients"},
        {"name": "CSS Shadow Gradients", "url": "https://alvarotrigo.com/shadow-gradients/", "description": "Generate CSS Gradients For Shadows"},
        {"name": "Creatica", "url": "https://creatica.app/backgrounds", "description": "Generate unique beautiful and unique Backgrounds and patterns"},
        {"name": "Boring Avatars", "url": "https://boringavatars.com/", "description": "SVG random, cutely avatars collections"},
        {"name": "fffuel", "url": "https://www.fffuel.co", "description": "Collection of color tools and free SVG generators for gradients, patterns, textures, shapes & backgrounds"},
        {"name": "Mesher", "url": "https://csshero.org/mesher", "description": "A Free tool to create beautiful mesh gradients only with CSS code"}
      ]
    },
    {
      "id": 2,
      "name": "Fonts",
      "slug": "fonts",
      "description": "Websites that offer free fonts as well as font-based tools",
      "resources": [
        {"name": "Google Fonts", "url": "https://fonts.google.com/", "description": "Library of around 1000 free licensed font families"},
        {"name": "DaFont", "url": "https://www.dafont.com/", "description": "Archive of freely downloadable fonts"},
        {"name": "Use & Modify", "url": "https://usemodify.com/", "description": "Personal selection of beautiful, classy, punk, professional typefaces"},
        {"name": "1001 Free Fonts", "url": "https://www.1001freefonts.com/", "description": "Collection of thousands of free typefaces"},
        {"name": "Font Squirrel", "url": "https://www.fontsquirrel.com/", "description": "High quality, legitimately free fonts"},
        {"name": "Font Fabric", "url": "https://www.fontfabric.com/free-fonts/", "description": "Digital type foundry offering retail fonts and custom typography"},
        {"name": "Just Free Fonts", "url": "https://justfreefonts.com/", "description": "Hand-curated collection of free fonts for commercial use"},
        {"name": "Tiff", "url": "https://winniethemu.github.io/tiff/", "description": "A type diff tool that visually contrasts differences between two fonts"},
        {"name": "TypeKit Practice", "url": "https://practice.typekit.com/", "description": "Learn about typography practices"},
        {"name": "Fontjoy", "url": "https://fontjoy.com/", "description": "Generate font pairing in one click"},
        {"name": "Golden Ratio Calculator", "url": "https://grtcalculator.com/", "description": "Golden Ratio Typography Calculator"},
        {"name": "FontGet", "url": "https://www.fontget.com/", "description": "Variety of fonts available to download, sorted neatly with tags"},
        {"name": "FontPair", "url": "https://fontpair.co/", "description": "Helps you pair Google Fonts together"},
        {"name": "Font Space", "url": "https://www.fontspace.com/", "description": "Designer-centered free font website with quick customizable previews"},
        {"name": "Abstract Fonts", "url": "http://www.abstractfonts.com/", "description": "Fonts free for personal and commercial use"},
        {"name": "Free Typography", "url": "https://freetypography.com/", "description": "A list of high quality fonts"},
        {"name": "Leon Sans", "url": "https://github.com/cmiscm/leonsans/", "description": "A geometric sans-serif typeface made with code"},
        {"name": "Lexend", "url": "https://www.lexend.com/", "description": "Variable font empirically shown to improve reading-proficiency"},
        {"name": "Fonts for Apple Platforms", "url": "https://developer.apple.com/fonts/", "description": "System fonts for Apple platforms in your apps"},
        {"name": "SFWin", "url": "https://github.com/blaisck/sfwin/", "description": "San Francisco Fonts for Windows 10 and non-Apple platforms"},
        {"name": "Font Flipper", "url": "https://fontflipper.com/", "description": "Preview 800+ Google Fonts on top of your own designs"},
        {"name": "Fonts Arena", "url": "https://fontsarena.com/", "description": "Free curated fonts"},
        {"name": "Befonts", "url": "https://befonts.com/", "description": "High quality fonts for free"},
        {"name": "Arabic Fonts", "url": "https://arabicfonts.net/", "description": "Arabic fonts available for free"},
        {"name": "FontDrop", "url": "https://fontdrop.info", "description": "Simple and easy way to view the contents of font files"},
        {"name": "Open Foundry", "url": "https://open-foundry.com", "description": "FREE platform for curated open-source typefaces"},
        {"name": "Glyphter", "url": "https://glyphter.com", "description": "Upload your own SVGs and turn them into font files"},
        {"name": "Google Webfonts Helper", "url": "https://gwfh.mranftl.com/fonts", "description": "A hassle-free way to self-host Google Fonts"},
        {"name": "Rough Font Awesome", "url": "https://djamshed.github.io/rough-awesome-font/dist/", "description": "When RoughJS meets Font Awesome"},
        {"name": "FFonts", "url": "https://ffonts.net", "description": "Stylish fonts for free"},
        {"name": "Malayalam Fonts", "url": "https://smc.org.in/fonts/", "description": "Malayalam fonts maintained by Swathanthra Malayalam Computing"},
        {"name": "Dev Fonts", "url": "https://devfonts.gafi.dev/", "description": "Find and use coding fonts for free"},
        {"name": "Font M", "url": "https://fontm.com/", "description": "Free fonts for material coding and design"},
        {"name": "W Fonts", "url": "https://www.wfonts.com/", "description": "Download free fonts"},
        {"name": "Modern Fluid Typography", "url": "https://modern-fluid-typography.vercel.app/", "description": "Fluid typography editor for responsive typography"},
        {"name": "UrbanFonts", "url": "https://www.urbanfonts.com/", "description": "Collection of over 8000 free fonts and dingbats"},
        {"name": "Typespiration", "url": "https://typespiration.com/", "description": "Inspirational font combinations and color palettes"},
        {"name": "Fontsource", "url": "https://fontsource.org/", "description": "Self-host Open Source fonts in NPM packages"},
        {"name": "FontBolt", "url": "https://www.fontbolt.com/", "description": "Discover and generate your favorite fonts from pop culture"},
        {"name": "Fontshare", "url": "https://www.fontshare.com/", "description": "Free fonts service from the Indian Type Foundry"}
      ]
    },
    {
      "id": 3,
      "name": "Colors",
      "slug": "colors",
      "description": "Websites and resources for color palettes, gradients, and color tools",
      "resources": [
        {"name": "Coolors", "url": "https://coolors.co/", "description": "The super fast color palettes generator"},
        {"name": "Color Hunt", "url": "https://colorhunt.co/", "description": "Free and open platform for color inspiration with thousands of trendy palettes"},
        {"name": "Adobe Color", "url": "https://color.adobe.com/", "description": "Create color palettes, extract gradients from images, and more"},
        {"name": "Flat UI Colors", "url": "https://flatuicolors.com/", "description": "Beautiful flat color palettes in various themes"},
        {"name": "Material Palette", "url": "https://www.materialpalette.com/", "description": "Material Design color palette generator"},
        {"name": "Colormind", "url": "http://colormind.io/", "description": "AI-powered color scheme generator"},
        {"name": "Khroma", "url": "http://khroma.co/", "description": "AI color tool that learns your preferences"},
        {"name": "Color Magic", "url": "https://colormagic.app/", "description": "AI-powered color palette generator"},
        {"name": "Mycolor.space", "url": "https://mycolor.space/", "description": "Generate nice color palettes from one color"},
        {"name": "Picular", "url": "https://picular.co/", "description": "Google, but for colors - search any word to get a palette"},
        {"name": "Happy Hues", "url": "https://www.happyhues.co/", "description": "Color palette inspiration site with real-world context"},
        {"name": "Color Box", "url": "https://colorbox.io/", "description": "Color tool by Lyft Design to create accessible color systems"},
        {"name": "Palettegenerator", "url": "https://palettegenerator.com/", "description": "Generate color palettes from images"},
        {"name": "Colorsinspo", "url": "https://colorsinspo.com/", "description": "All-in-one resource for finding color inspirations"},
        {"name": "Color Leap", "url": "https://colorleap.app/", "description": "Take a leap through time and see the colors of history"},
        {"name": "Muzli Colors", "url": "https://colors.muz.li/", "description": "Search, discover, and test color palettes"},
        {"name": "Farbvelo", "url": "https://farbvelo.elastiq.ch/", "description": "Random color palette generator"},
        {"name": "Veranda Color", "url": "https://verandacolor.com", "description": "Browse, search, and curate color collections"},
        {"name": "Duo", "url": "https://duo.alexpate.uk/", "description": "Collection of color combinations"},
        {"name": "Lospec", "url": "https://lospec.com/", "description": "Pixel art palettes and tools"},
        {"name": "Egg Gradients", "url": "https://www.eggradients.com/", "description": "Collection of beautiful gradient colors"},
        {"name": "Gradientos", "url": "https://www.gradientos.app/", "description": "Find beautiful gradients to use in your projects"},
        {"name": "Encycolorpedia", "url": "https://encycolorpedia.com/", "description": "Color encyclopedia with detailed information"},
        {"name": "Chroma", "url": "https://chroma.dev/", "description": "Free collection of hand-curated color palettes"},
        {"name": "Color Designer", "url": "https://colordesigner.io/", "description": "Simple color palette generator"},
        {"name": "Duotone", "url": "https://duotone.shapefactory.co/", "description": "Find beautiful free duotone images"},
        {"name": "Cool Backgrounds", "url": "https://coolbackgrounds.io/", "description": "Collection of tools to create compelling backgrounds"},
        {"name": "Color Shades", "url": "https://mdigi.tools/color-shades/", "description": "Generate shades and tints of a color"},
        {"name": "Huemint", "url": "https://huemint.com/", "description": "AI color palette generator for brands and graphics"},
        {"name": "Inclusive Colors", "url": "https://www.inclusivecolors.com/", "description": "Accessible color palette generator"},
        {"name": "Brandfolder Color Palette", "url": "https://brandfolder.com/workbench/color-palette", "description": "Generate color palettes from images"},
        {"name": "UI Gradient", "url": "https://uigradients.com/", "description": "Beautiful colored gradients collection"},
        {"name": "Web Gradients", "url": "https://webgradients.com/", "description": "Free collection of 180 linear gradients"},
        {"name": "Grabient", "url": "https://www.grabient.com/", "description": "Beautiful and simple UI for generating gradients"},
        {"name": "CSS Gradient", "url": "https://cssgradient.io/", "description": "Free CSS gradient generator tool"},
        {"name": "Gradient Hunt", "url": "https://gradienthunt.com/", "description": "Platform for color gradients"},
        {"name": "Gradienta", "url": "https://gradienta.io/", "description": "Multicolor CSS gradients"},
        {"name": "Who Can Use", "url": "https://www.whocanuse.com/", "description": "Tool to check color contrast for accessibility"},
        {"name": "Colorable", "url": "https://colorable.jxnblk.com/", "description": "Color accessibility contrast checker"},
        {"name": "Color Review", "url": "https://color.review/", "description": "Colors that look and work great for everyone"},
        {"name": "Pigment", "url": "https://pigment.shapefactory.co/", "description": "Simple color palette generator"},
        {"name": "Colorzilla", "url": "https://www.colorzilla.com/", "description": "Advanced eyedropper and color picker extension"},
        {"name": "Paletton", "url": "https://paletton.com", "description": "Color scheme designer"},
        {"name": "Saruwakakun Color Ideas", "url": "https://saruwakakun.com/en/color-ideas", "description": "Beautiful color scheme combinations"},
        {"name": "HTML CSS Color", "url": "https://htmlcsscolor.com/", "description": "Color code picker and converter"},
        {"name": "Hex Color Codes", "url": "https://hexcolorcodes.org/", "description": "Color picker and color codes"},
        {"name": "CoolHue", "url": "https://webkul.github.io/coolhue/", "description": "Handpicked gradient palette"},
        {"name": "Colors.lol", "url": "https://colors.lol/", "description": "Overly descriptive color palettes"},
        {"name": "Dopely Colors", "url": "https://colors.dopely.top/", "description": "Color palette generator"},
        {"name": "UI Color Picker", "url": "https://uicolorpicker.com/", "description": "iOS and macOS color picker"},
        {"name": "Color-Hex", "url": "https://www.color-hex.com/", "description": "Color information and conversions"},
        {"name": "Brand Colors", "url": "https://brandcolors.net/", "description": "Official brand color codes"},
        {"name": "Color Safe", "url": "http://colorsafe.co/", "description": "Accessible web color combinations based on WCAG"},
        {"name": "Color Curves", "url": "https://colorcurves.app/", "description": "Color palette generator with curve-based editing"},
        {"name": "Color Contrast Checker", "url": "https://colorcontrastchecker.com/", "description": "Check WCAG contrast ratios"},
        {"name": "Color Hailpixel", "url": "https://color.hailpixel.com/", "description": "Colorful thinking tool"},
        {"name": "Combine Colors", "url": "https://www.combinecolors.com/", "description": "Color mixing tool"}
      ]
    },
    {
      "id": 4,
      "name": "Icons",
      "slug": "icons",
      "description": "Resources for icons including icon libraries, icon fonts, and icon tools",
      "resources": [
        {"name": "Circum Icons", "url": "https://circumicons.com/", "description": "Consistent open source icons as SVG for React, Vue and Svelte"},
        {"name": "UXWing", "url": "https://uxwing.com/", "description": "Well optimized, free icons for commercial use"},
        {"name": "Shapedfonts Iconclub", "url": "https://shapedfonts.com/iconclub/", "description": "8000+ free icons"},
        {"name": "Feather Icons", "url": "https://feathericons.com/", "description": "Beautiful, customizable open source icons"},
        {"name": "Tabler Icons", "url": "https://tabler-icons.io/", "description": "3500+ highly customizable open source SVG icons"},
        {"name": "Xicons", "url": "https://www.xicons.org/#/", "description": "SVG Vue/React components integrated from multiple icon sets"},
        {"name": "Iconoir", "url": "https://iconoir.com/", "description": "Free library of 900+ open source icons"},
        {"name": "Simple Icons", "url": "https://simpleicons.org/", "description": "1307 free SVG icons for popular brands"},
        {"name": "Linear Icons", "url": "https://linearicons.com/free", "description": "1000+ ultra crisp vector icons"},
        {"name": "Icons8", "url": "https://icons8.com/", "description": "Free icons, photos, vectors and tools"},
        {"name": "Flat Icon", "url": "https://www.flaticon.com/", "description": "The largest database of free icons in PNG, SVG, EPS, PSD and BASE 64 formats"},
        {"name": "The Noun Project", "url": "https://thenounproject.com/", "description": "Over 2 million curated icons created by a global community"},
        {"name": "Iconscout", "url": "https://iconscout.com/", "description": "Free download icons, illustrations and stock photos"},
        {"name": "IconSear.ch", "url": "https://iconsear.ch/search.html", "description": "Search engine with over 50,000 SVG icons indexed"},
        {"name": "Nucleo App", "url": "https://nucleoapp.com/", "description": "Beautiful library of 27,500 icons (free and paid)"},
        {"name": "Icon-icons.com", "url": "https://icon-icons.com/", "description": "Free icons in PNG, ICO, ICNS and SVG vector file formats"},
        {"name": "Bootstrap Icons", "url": "https://icons.getbootstrap.com/", "description": "Free icons built for Bootstrap but work in any project"},
        {"name": "Remix Icon", "url": "https://remixicon.com/", "description": "Simply delightful icon system"},
        {"name": "Iconmonstr", "url": "https://iconmonstr.com/", "description": "Discover 4496+ free icons in 313 collections"},
        {"name": "Vivid.js", "url": "https://webkul.github.io/vivid/", "description": "Ready to use free and open source SVG icons pack JavaScript library"},
        {"name": "Iconfinder", "url": "https://www.iconfinder.com/", "description": "Free and premium vector icons in SVG, PNG, CSH and AI format"},
        {"name": "Lordicon", "url": "https://lordicon.com/icons#free", "description": "50 free animated interactive icons"},
        {"name": "UseAnimations", "url": "https://useanimations.com/", "description": "Free animated icons in SVG and JSON format for Lottie"},
        {"name": "css.gg", "url": "https://css.gg/", "description": "700+ open-source CSS, SVG and Figma UI icons"},
        {"name": "Material Design Icons", "url": "https://materialdesignicons.com/", "description": "Icon collection for designers and developers to download"},
        {"name": "Heroicons", "url": "https://heroicons.dev/", "description": "Free, open source icons from the creators of Tailwind CSS"},
        {"name": "Zondicons", "url": "https://www.zondicons.com/icons.html", "description": "Set of free premium SVG icons for digital products"},
        {"name": "Endless Icons", "url": "http://endlessicons.com/", "description": "Website offering free icons"},
        {"name": "Icomoon", "url": "https://icomoon.io/app/", "description": "Browse 5500+ free icons"},
        {"name": "Eva Icons", "url": "https://akveo.github.io/eva-icons/#/", "description": "Pack of more than 480 beautifully crafted open source icons"},
        {"name": "Ikonate", "url": "https://ikonate.com/", "description": "Fully customizable and accessible vector icons"},
        {"name": "appicon", "url": "https://appicon.co/", "description": "Quickly generate app icons in different sizes for iOS, macOS and Android"},
        {"name": "LineIcons", "url": "https://lineicons.com", "description": "2000+ essential line icons for designers and developers"},
        {"name": "Evericons", "url": "https://www.figma.com/resources/assets/evericons-for-figma/", "description": "Big pack of over 460 free icons designed by Aleksey Popov"},
        {"name": "SVG Repo", "url": "https://www.svgrepo.com/", "description": "Download free SVG vectors for commercial use"},
        {"name": "Convertio", "url": "https://convertio.co/png-svg/", "description": "Convert PNG files to SVG online for free"},
        {"name": "CSS ICON", "url": "https://cssicon.space/", "description": "Icon set made with pure CSS code, no dependencies"},
        {"name": "Iconify", "url": "https://iconify.design/", "description": "Thousands of icons, one unified framework with over 40,000 vector icons"},
        {"name": "System UIcons", "url": "https://systemuicons.com/", "description": "220+ icons in a growing collection"},
        {"name": "IconPark", "url": "https://github.com/bytedance/IconPark", "description": "Transform an SVG icon into multiple themes"},
        {"name": "Radix Icons", "url": "https://www.radix-ui.com/icons", "description": "Crisp set of 15x15 icons designed by the Modulz team"},
        {"name": "Ionicons", "url": "https://ionicons.com", "description": "Beautifully crafted open source icons for web, iOS, Android"},
        {"name": "Phosphor Icons", "url": "https://phosphoricons.com", "description": "Flexible icon family for interfaces, diagrams, presentations"},
        {"name": "Teeny Icons", "url": "https://teenyicons.com/", "description": "Set of icons in SVG format easy to use in HTML"},
        {"name": "Lucide", "url": "https://lucide.netlify.app/", "description": "Open-source icon library, a fork of Feather Icons"},
        {"name": "Icones", "url": "https://icones.js.org/", "description": "Icon explorer with instant searching, powered by Iconify"},
        {"name": "Shitty Icons", "url": "https://shittyicons.com/", "description": "Collection of free icons"},
        {"name": "iconhub", "url": "https://iconhub.io/", "description": "Practical stunning icons for everyone"},
        {"name": "3DICONS", "url": "https://3dicons.co", "description": "Beautifully crafted open source 3D icons"},
        {"name": "IconsDb", "url": "https://www.iconsdb.com/", "description": "Free custom icons"},
        {"name": "Emoji Guide", "url": "https://emojiguide.org/", "description": "Collection of 3300 emojis with HTML codes for easy use"},
        {"name": "Unicorn Icons", "url": "https://unicornicons.com", "description": "100+ customizable playful animated icons"},
        {"name": "Sargam Icons", "url": "https://sargamicons.com/", "description": "Collection of 275+ open-source icons for Figma, SVGs, and React"},
        {"name": "Icon Buddy", "url": "https://iconbuddy.app/", "description": "Collection of 100K+ open-source SVG icons, fully customizable"},
        {"name": "Round Icons", "url": "https://roundicons.com/", "description": "World's biggest premium and free icon packs library"},
        {"name": "Vectopus", "url": "https://vectopus.com", "description": "Top curated collective resources for elite designers"},
        {"name": "IconShelf", "url": "https://iconshelf.com/", "description": "Access 250,000+ open-source SVG icons you can customize"}
      ]
    },
    {
      "id": 5,
      "name": "Logos",
      "slug": "logos",
      "description": "Resources for logo design and logo assets",
      "resources": [
        {"name": "LogoSear.ch", "url": "https://logosear.ch/search.html", "description": "Search engine with over 200,000 SVG logos indexed"},
        {"name": "SVGPorn", "url": "https://svgporn.com", "description": "1000+ high-quality SVG logos"},
        {"name": "Payment System Logos", "url": "https://github.com/mpay24/payment-logos/", "description": "Logos for payment systems available in PNG and SVG"},
        {"name": "Browser Logos", "url": "https://github.com/alrra/browser-logos/", "description": "High resolution web browser logos"},
        {"name": "VectorLogoZone", "url": "https://www.vectorlogo.zone/", "description": "Consistently formatted SVG logos"},
        {"name": "World Vector Logo", "url": "https://worldvectorlogo.com/", "description": "Download vector logos of brands you love"},
        {"name": "Logo Maker", "url": "https://logomakr.com/", "description": "Create custom logos"},
        {"name": "LOGOwine", "url": "https://www.logo.wine/", "description": "Brand logos free download in SVG vector and PNG file format"}
      ]
    },
    {
      "id": 6,
      "name": "Favicons",
      "slug": "favicons",
      "description": "Resources for favicon generation and favicon assets",
      "resources": [
        {"name": "Favicon.io", "url": "https://favicon.io/", "description": "Generate a favicon from text, from an image, or from an emoji"},
        {"name": "Favicomatic", "url": "https://favicomatic.com/", "description": "Generate favicons of all sizes and formats with HTML code for all browsers"},
        {"name": "RealFaviconGenerator", "url": "https://realfavicongenerator.net/", "description": "Generate icons for all platforms (Windows, iOS, Android)"},
        {"name": "FontIcon", "url": "https://gauger.io/fonticon/", "description": "Generate favicons and images from Font Awesome icons"},
        {"name": "Favicon.cc", "url": "https://www.favicon.cc", "description": "Draw a favicon online and browse through a library of favicons"},
        {"name": "Maskable.app Editor", "url": "https://maskable.app/editor/", "description": "Generate maskable PWA icons based on your existing icon"},
        {"name": "Favicon Generator", "url": "https://favicon.inbrowser.app/", "description": "Generate website's favicon assets with SVG and maskable support"},
        {"name": "FaviFiles", "url": "https://favifiles.com/", "description": "Generate pixel-perfect favicons for free in seconds"}
      ]
    },
    {
      "id": 7,
      "name": "Icon Fonts",
      "slug": "icon-fonts",
      "description": "Resources for icon fonts and web font icons",
      "resources": [
        {"name": "Font Awesome", "url": "https://fontawesome.com/", "description": "The web's most popular icon set and toolkit"},
        {"name": "Line Awesome", "url": "https://icons8.com/line-awesome", "description": "Swap in replacement of Font Awesome with modern line icons"},
        {"name": "IonIcons", "url": "http://ionicons.com/", "description": "Beautifully crafted open source icons from Ionic team"},
        {"name": "Zurb Foundation Icons", "url": "https://zurb.com/playground/foundation-icon-fonts-3", "description": "Customizable Foundation icons"},
        {"name": "Boxicons", "url": "https://boxicons.com/", "description": "Free collection of carefully crafted open source icons"},
        {"name": "Icofont", "url": "https://icofont.com/", "description": "2100+ free icons to spice up your creative designs"},
        {"name": "Material Design Iconic Font", "url": "http://zavoloklom.github.io/material-design-iconic-font/index.html", "description": "Material design icon font"},
        {"name": "Vscode Codicons", "url": "https://microsoft.github.io/vscode-codicons/dist/codicon.html", "description": "The icon font from Visual Studio Code"},
        {"name": "Devicon", "url": "https://devicon.dev", "description": "Set of icons representing programming languages and development tools"},
        {"name": "PaymentFont", "url": "https://github.com/AlexanderPoellmann/PaymentFont", "description": "A sleek web font for payment operators and methods with 116 icons"},
        {"name": "Weather Icons", "url": "https://erikflowers.github.io/weather-icons/", "description": "Weather Icons is the only icon font with 222 weather themed icons"},
        {"name": "Stroke 7", "url": "https://themes-pixeden.com/font-demos/7-stroke/index.html", "description": "202 thin stroke icons inspired by iOS 7"},
        {"name": "Jam Icons", "url": "https://jam-icons.com/", "description": "890+ handcrafted icons to make your web app awesome"},
        {"name": "Fontello", "url": "http://fontello.com/", "description": "200+ web icons where you can customize the names or codes of icons"},
        {"name": "Linea", "url": "https://linea.io/", "description": "Linea featuring 750+ free icons"},
        {"name": "Unicons", "url": "https://iconscout.com/unicons", "description": "A set of 1100+ free line style icons for web fonts, SVG, and JS frameworks"},
        {"name": "Mobirise Icons", "url": "https://mobiriseicons.com/", "description": "A free, open source set of 150 elegant, pixel-perfect linear icons"},
        {"name": "Hero Icons", "url": "https://heroicons.dev/", "description": "Free open source SVG icon library"},
        {"name": "React Icons", "url": "https://react-icons.github.io/react-icons/", "description": "Open source and free SVG icon library, collection of popular icon libraries"}
      ]
    },
    {
      "id": 8,
      "name": "Stock Photos",
      "slug": "stock-photos",
      "description": "Websites that offer free stock photos for commercial and personal use",
      "resources": [
        {"name": "Pexels", "url": "https://www.pexels.com/", "description": "Free stock photos shared by talented creators"},
        {"name": "Unsplash", "url": "https://unsplash.com/", "description": "The internet's source of freely usable images"},
        {"name": "Pixabay", "url": "https://pixabay.com/", "description": "Over 1.7 million+ high-quality stock images and videos"},
        {"name": "Magdeleine", "url": "https://magdeleine.co/", "description": "Gallery and free high-resolution photo everyday"},
        {"name": "Picspree", "url": "https://picspree.com", "description": "Royalty free images, stock photos, illustrations, and vectors"},
        {"name": "Burst", "url": "https://burst.shopify.com/", "description": "Free stock photos collections"},
        {"name": "Gratisography", "url": "https://gratisography.com/", "description": "Free collection of free high-resolution pictures"},
        {"name": "Life of Pix", "url": "https://www.lifeofpix.com/", "description": "Free high-resolution photography"},
        {"name": "Stock Snap", "url": "https://stocksnap.io/", "description": "Hundreds of high quality photos added weekly"},
        {"name": "Morguefile", "url": "https://morguefile.com/", "description": "Over 350,000 free stock photos for commercial use"},
        {"name": "Kaboom Pics", "url": "https://kaboompics.com/", "description": "Stock photography and color palettes for product images"},
        {"name": "New Old Stock", "url": "https://nos.twnsnd.co/", "description": "Stock vintage photos"},
        {"name": "Pic Jumbo", "url": "https://picjumbo.com/", "description": "Good collections of different types of photos"},
        {"name": "Public Domain Pictures", "url": "https://www.publicdomainpictures.net/en/", "description": "Public domain images of all types"},
        {"name": "Find A Photo", "url": "https://www.chamberofcommerce.org/findaphoto/", "description": "Searches multiple stock photo websites"},
        {"name": "Stockvault", "url": "http://www.stockvault.net/", "description": "Categorized stock photos"},
        {"name": "Realistic Shots", "url": "https://realisticshots.com/", "description": "Free high-resolution stock photos"},
        {"name": "Negative Space", "url": "https://negativespace.co/", "description": "High-resolution free stock photos"},
        {"name": "SkitterPhoto", "url": "https://skitterphoto.com/", "description": "Free high-resolution photography"},
        {"name": "PicoGraphy", "url": "https://picography.co/", "description": "Gorgeous, high-resolution, free photos"},
        {"name": "PxHere", "url": "https://pxhere.com/", "description": "Free images and free stock photos"},
        {"name": "Piqsels", "url": "https://piqsels.com/", "description": "Royalty free stock photos"},
        {"name": "FoodiesFeed", "url": "https://www.foodiesfeed.com/", "description": "Food photo stock"},
        {"name": "Nappy", "url": "https://www.nappy.co/", "description": "Beautiful, high-res photos of black and brown people"},
        {"name": "Generated Photos", "url": "https://generated.photos/", "description": "Unique AI generated model photos"},
        {"name": "Reshot", "url": "https://www.reshot.com/", "description": "Uniquely free photos, handpicked, non-stocky images"},
        {"name": "Free Images", "url": "https://www.freeimages.com/", "description": "Find and download free stock photos"},
        {"name": "Lorem Picsum", "url": "https://picsum.photos/", "description": "Easy to use API for beautiful placeholder images"},
        {"name": "IAN Image Library", "url": "https://ian.umces.edu/imagelibrary", "description": "Free images for science communication"},
        {"name": "Saxifraga", "url": "http://www.freenatureimages.eu", "description": "Free nature images"},
        {"name": "Creative Commons", "url": "https://search.creativecommons.org", "description": "Search for free images to reuse"},
        {"name": "AllTheFreeStock", "url": "https://allthefreestock.com/", "description": "Curated list of free stock images, audio and videos"},
        {"name": "Lorem.space", "url": "https://lorem.space", "description": "API for placeholder images"},
        {"name": "Openverse", "url": "https://wordpress.org/openverse/", "description": "Search engine for openly-licensed media"},
        {"name": "ISO Republic", "url": "https://isorepublic.com/", "description": "Thousands of free high-resolution stock CC0 photos"}
      ]
    },
    {
      "id": 9,
      "name": "Stock Videos",
      "slug": "stock-videos",
      "description": "Websites that offer free stock videos for commercial and personal use",
      "resources": [
        {"name": "Pexels Videos", "url": "https://www.pexels.com/videos", "description": "Largest library of free to use videos, donated by the community"},
        {"name": "Pixabay Videos", "url": "https://www.pixabay.com/videos", "description": "Large library of free to use videos, donated by the community"},
        {"name": "Coverr", "url": "https://coverr.co/", "description": "Beautiful free stock video footage"},
        {"name": "Videezy", "url": "https://www.videezy.com/", "description": "Free HD stock footage and 4K videos"},
        {"name": "Mixkit", "url": "https://mixkit.co/", "description": "Stock video clips and music"},
        {"name": "Videvo", "url": "https://www.videvo.net/stock-video-footage/", "description": "Free and premium stock videos"},
        {"name": "SplitShire", "url": "https://www.splitshire.com/", "description": "Beautiful and exclusive free stock videos and photos"},
        {"name": "Free Stock Video", "url": "https://free-stock.video", "description": "Free footage stock videos"}
      ]
    },
    {
      "id": 10,
      "name": "Stock Music & Sound Effects",
      "slug": "stock-music-sound-effects",
      "description": "Websites that offer free music and sound effects for projects",
      "resources": [
        {"name": "YouTube Studio Audio Library", "url": "https://www.youtube.com/audiolibrary", "description": "Royalty-free audio library for downloadable music and sound effects, cleared for YouTube monetization"},
        {"name": "Free Stock Music", "url": "https://www.free-stock-music.com/", "description": "Royalty free stock music for YouTube videos, podcasts, and similar projects"},
        {"name": "Bensound", "url": "https://www.bensound.com/", "description": "Download royalty free music for free and use it in your project"},
        {"name": "Mixkit Music", "url": "https://mixkit.co/free-stock-music/", "description": "Free music available for creative projects"},
        {"name": "Freesound", "url": "https://freesound.org/", "description": "Free stock music and sounds"},
        {"name": "Free Music Archive", "url": "https://freemusicarchive.org/", "description": "Collaborative database of creative-commons licensed sound for musicians"},
        {"name": "Musopen", "url": "https://musopen.org/music/", "description": "Online copyright free classical music library"},
        {"name": "Pixabay Music", "url": "https://pixabay.com/music/", "description": "Free music downloads for YouTube videos, vlogs, films, and podcasts"},
        {"name": "Unminus", "url": "https://www.unminus.com/", "description": "Free premium music for your projects, royalty free and cleared for YouTube"}
      ]
    },
    {
      "id": 11,
      "name": "Vectors & Clip Art",
      "slug": "vectors-clip-art",
      "description": "Free vectors, clipart, illustrations, and patterns",
      "resources": [
        {"name": "PNGFree.ai", "url": "https://pngfree.ai/", "description": "Millions of high-quality free PNG images"},
        {"name": "Vecteezy", "url": "https://www.vecteezy.com/", "description": "Find and download free vector art"},
        {"name": "Freepik", "url": "https://www.freepik.com", "description": "Free vectors, stock photos, PSD and icons"},
        {"name": "Free Vectors", "url": "https://www.freevectors.net/", "description": "Community of vector lovers sharing free vector graphics"},
        {"name": "PNGTree", "url": "https://pngtree.com/free-vectors", "description": "PNG, backgrounds, templates, text effects"},
        {"name": "Vector4Free", "url": "https://www.vector4free.com/", "description": "Free vector graphics"},
        {"name": "Freeble", "url": "http://freebbble.com/", "description": "Vectors, patterns, mockups and more"},
        {"name": "Lukaszadam", "url": "https://lukaszadam.com/", "description": "Free vector artworks"},
        {"name": "Illlustrations", "url": "https://illlustrations.co/", "description": "Beautiful 100 illustrations in PNG and SVG"},
        {"name": "Clipart", "url": "https://www.clipart.email/", "description": "Clipart, PNG, coloring pages, drawings for projects"},
        {"name": "Trianglify", "url": "https://trianglify.io/", "description": "Generate low-poly backgrounds, textures, and vectors"},
        {"name": "Blob Maker", "url": "https://blobs.app/", "description": "Generate blob shapes for web and Flutter apps"},
        {"name": "HiClipart", "url": "https://www.hiclipart.com/", "description": "Community for transparent background PNG cliparts"},
        {"name": "Black Illustrations", "url": "https://www.blackillustrations.com/", "description": "Beautiful illustrations of black people, free and premium"},
        {"name": "Delesign", "url": "https://delesign.com/free-designs/graphics", "description": "Collection of free illustrations and more"},
        {"name": "Custom Shape Dividers", "url": "https://www.shapedivider.app/", "description": "Export beautiful SVG shape dividers"},
        {"name": "Servier Medical Art", "url": "https://smart.servier.com", "description": "3000 free medical images for publications"},
        {"name": "SVG Wave", "url": "https://svgwave.in/", "description": "Free, customizable gradient SVG wave generator"},
        {"name": "BGjar", "url": "https://bgjar.com", "description": "Free SVG background generator"},
        {"name": "Heritage Library", "url": "https://www.heritagetype.com/collections/free-vintage-illustrations", "description": "Vintage illustrations in vector and PNG formats"},
        {"name": "RoboHash", "url": "https://robohash.org/", "description": "Generate unique images from any text"},
        {"name": "Tabbied", "url": "https://tabbied.com/", "description": "Create and customize minimally generated patterns and artwork"},
        {"name": "Haikei", "url": "https://app.haikei.app/", "description": "Multishape web app for design elements"},
        {"name": "Vector.ma", "url": "https://vector.ma/", "description": "Moroccan vectors collection"},
        {"name": "Heazy", "url": "https://app.heazy.studio/", "description": "Unique vector assets within seconds"},
        {"name": "Mossaik", "url": "https://mossaik.app/", "description": "Free SVG generator with waves, tiles, blobs, and more"}
      ]
    },
    {
      "id": 12,
      "name": "Product & Image Mockups",
      "slug": "product-image-mockups",
      "description": "Create mockups for products, devices, and app screenshots",
      "resources": [
        {"name": "MockCity", "url": "https://mockcity.com/", "description": "Bulk generate mockups from PSD templates by automatically placing images in SmartObjects"},
        {"name": "Smart Mockups", "url": "https://smartmockups.com/", "description": "Create stunning product mockups, free and premium"},
        {"name": "Media Modifier", "url": "https://mediamodifier.com/", "description": "Beautiful design mockups service for your products"},
        {"name": "Shot Snap", "url": "https://shotsnapp.com/", "description": "Create beautiful device mockup images for your app or website design"},
        {"name": "Screely", "url": "https://www.screely.com/", "description": "Instantly turn your screenshot into a mockup"},
        {"name": "Screenshot.rocks", "url": "https://screenshot.rocks/", "description": "Create beautiful browser and mobile mockups in seconds"},
        {"name": "Screen Peak", "url": "https://screenpeek.io/", "description": "Create a mockup from a URL"},
        {"name": "Mockup World", "url": "https://www.mockupworld.co/", "description": "The biggest source of free photo-realistic mockups online"},
        {"name": "Collab Shot", "url": "https://www.collabshot.com/", "description": "Real-time screen grabs and image sharing"},
        {"name": "Mockuphone", "url": "https://mockuphone.com/", "description": "100% free mockups for all devices including iOS, Android, Windows Phone, Laptop and TV"},
        {"name": "Device Shots", "url": "https://deviceshots.com/", "description": "Create high-resolution device mockups for social media, for free"},
        {"name": "Clean Mock", "url": "https://cleanmock.com/", "description": "Create stunning mockups using latest device frames like iPhone X"},
        {"name": "Mock.Video", "url": "https://www.mock.video/", "description": "Instantly create mockups by adding a device frame to your videos"},
        {"name": "MockupBro", "url": "https://mockupbro.com/", "description": "Create product mockups with online mockup generator without watermark"},
        {"name": "Animockup", "url": "https://github.com/alyssaxuu/animockup", "description": "Create animated mockups in the browser"},
        {"name": "Pika", "url": "https://pika.style", "description": "Instantly create browser mockups and beautiful images for marketing"},
        {"name": "Lunacy", "url": "https://icons8.com/lunacy", "description": "Create mockups from scratch for free"}
      ]
    },
    {
      "id": 13,
      "name": "UI Components & Kits",
      "slug": "ui-components-kits",
      "description": "UI component libraries and design kits for building modern web applications",
      "resources": [
        {"name": "UILang", "url": "http://uilang.com/", "description": "A minimal, UI-focused programming language for web designers"},
        {"name": "Medialoot CSS Components", "url": "https://medialoot.com/free-themes/css-components/", "description": "Calendars, price grids and other UI components"},
        {"name": "Froala Design Blocks", "url": "https://froala.com/design-blocks", "description": "Over 170 responsive design blocks ready for web or mobile apps"},
        {"name": "Material Design For Bootstrap", "url": "https://fezvrasta.github.io/bootstrap-material-design/", "description": "Open source toolkit for building material design with Bootstrap"},
        {"name": "Photonkit", "url": "http://photonkit.com/", "description": "Desktop UI library for Electron"},
        {"name": "Flat UI", "url": "https://designmodo.github.io/Flat-UI/", "description": "Minimal free user interface kit"},
        {"name": "Shards", "url": "https://designrevision.com/downloads/shards/", "description": "Modern UI toolkit for web makers based on Bootstrap"},
        {"name": "Creative Tim", "url": "https://www.creative-tim.com/", "description": "UI libraries and kits including JS frameworks like React"},
        {"name": "Brumm Shadow Maker", "url": "https://brumm.af/shadows", "description": "Online tool to make CSS shadows"},
        {"name": "SpinKit", "url": "https://tobiasahlin.com/spinkit/", "description": "Simple CSS Spinners"},
        {"name": "Moving Letters", "url": "https://tobiasahlin.com/moving-letters/", "description": "Animated Text with JavaScript and anime.js"},
        {"name": "CSS Layout", "url": "https://csslayout.io/", "description": "Popular web layouts and patterns in pure CSS"},
        {"name": "Codyhouse", "url": "https://codyhouse.co/", "description": "Front-end framework with accessible HTML, CSS, JavaScript components"},
        {"name": "Tailwind Starter Kit", "url": "https://github.com/creativetimofficial/tailwind-starter-kit", "description": "Beautiful extension for TailwindCSS"},
        {"name": "Tailwindtoolbox", "url": "https://www.tailwindtoolbox.com/", "description": "Starter templates, components, and utilities for Tailwind CSS"},
        {"name": "tailwindcomponents", "url": "https://tailwindcomponents.com/", "description": "Free community components using TailwindCSS"},
        {"name": "Material-UI", "url": "https://material-ui.com/", "description": "React components for faster and easier web development"},
        {"name": "Chakra UI", "url": "https://chakra-ui.com/", "description": "Simple, accessible component library for React"},
        {"name": "Ant Design", "url": "https://ant.design/", "description": "Enterprise-class UI design system"},
        {"name": "Semantic UI", "url": "https://semantic-ui.com/", "description": "User-friendly component framework"},
        {"name": "Storybook", "url": "https://storybook.js.org/", "description": "Development environment for UI components"},
        {"name": "shadcn/ui", "url": "https://ui.shadcn.com/", "description": "High-quality React components you can copy/paste"},
        {"name": "Headless UI", "url": "https://headlessui.com/", "description": "Unstyled accessible components for React/Vue"},
        {"name": "Daisy UI", "url": "https://daisyui.com/", "description": "Component library built on Tailwind CSS"},
        {"name": "Mantine", "url": "https://mantine.dev/", "description": "React components and hooks library with TypeScript support"},
        {"name": "NextUI", "url": "https://nextui.org/", "description": "Modern React UI library with beautiful defaults"},
        {"name": "UIkit", "url": "https://getuikit.com/", "description": "Lightweight and modular front-end framework"},
        {"name": "Evergreen", "url": "https://evergreen.segment.com/", "description": "React UI framework by Segment"},
        {"name": "Grommet", "url": "https://v2.grommet.io/", "description": "React-based framework for building responsive apps"},
        {"name": "Rebass", "url": "https://rebassjs.org/", "description": "Primitive React UI components using styled-system"},
        {"name": "Blueprint", "url": "https://blueprintjs.com/", "description": "React-based UI toolkit for web applications"},
        {"name": "Fluent UI", "url": "https://developer.microsoft.com/en-us/fluentui", "description": "Microsoft's design system and components"}
      ]
    },
    {
      "id": 14,
      "name": "HTML & CSS Templates",
      "slug": "html-css-templates",
      "description": "Websites that offer free HTML & CSS templates",
      "resources": [
        {"name": "HTML5Up", "url": "https://html5up.net/", "description": "Very modern, unique responsive HTML5/CSS3 themes"},
        {"name": "Templatemo", "url": "https://templatemo.com/", "description": "Minimal, resume, gallery themes and more"},
        {"name": "Templated.co", "url": "https://templated.co/", "description": "Tons of minimalistic HTML5/CSS3 themes"},
        {"name": "FreeHTML5", "url": "https://freehtml5.co/", "description": "Free & premium HTML5 and Bootstrap themes"},
        {"name": "StyleShout", "url": "https://www.styleshout.com/free-templates/", "description": "Brilliantly crafted free website templates"},
        {"name": "Start Bootstrap", "url": "https://startbootstrap.com/", "description": "Bootstrap starter themes"},
        {"name": "Colorlib", "url": "https://colorlib.com/wp/templates/", "description": "Almost any category of theme you can think of"},
        {"name": "Hubspot", "url": "https://www.hubspot.com/resources", "description": "Templates, infographics, banners and much more"},
        {"name": "Mobirise", "url": "https://mobirise.com/html-templates/", "description": "Great looking HTML5/CSS3 templates"},
        {"name": "Bootswatch", "url": "https://bootswatch.com/", "description": "Free themes for Bootstrap"},
        {"name": "Onepagelove", "url": "https://onepagelove.com/", "description": "One page websites, templates and resources"},
        {"name": "Themes For App", "url": "https://themesfor.app/", "description": "Free Bootstrap themes and landing pages"},
        {"name": "BootstrapTaste", "url": "https://bootstraptaste.com/", "description": "Premium & Free Bootstrap Templates"},
        {"name": "BootstrapMade", "url": "https://bootstrapmade.com/", "description": "Elegant, clean and beautiful free templates using Bootstrap"},
        {"name": "W3Layouts", "url": "https://w3layouts.com/", "description": "Thousands of free website templates"}
      ]
    },
    {
      "id": 15,
      "name": "CSS Frameworks",
      "slug": "css-frameworks",
      "description": "CSS and UI frameworks for building responsive websites",
      "resources": []
    },
    {
      "id": 16,
      "name": "CSS Methodologies",
      "slug": "css-methodologies",
      "description": "CSS methodologies and architectural patterns for scalable CSS",
      "resources": []
    },
    {
      "id": 17,
      "name": "CSS Animations",
      "slug": "css-animations",
      "description": "CSS animation libraries and tools",
      "resources": []
    },
    {
      "id": 18,
      "name": "Javascript Animation Libraries",
      "slug": "javascript-animation-libraries",
      "description": "JavaScript libraries for animations and motion effects",
      "resources": []
    },
    {
      "id": 19,
      "name": "Javascript Chart Libraries",
      "slug": "javascript-chart-libraries",
      "description": "JavaScript libraries for data visualization and charts",
      "resources": []
    },
    {
      "id": 20,
      "name": "React UI Libraries",
      "slug": "react-ui-libraries",
      "description": "UI component libraries for React",
      "resources": []
    },
    {
      "id": 21,
      "name": "Vue UI Libraries",
      "slug": "vue-ui-libraries",
      "description": "UI component libraries for Vue.js",
      "resources": []
    },
    {
      "id": 22,
      "name": "Angular UI Libraries",
      "slug": "angular-ui-libraries",
      "description": "UI component libraries for Angular",
      "resources": []
    },
    {
      "id": 23,
      "name": "Svelte UI Libraries",
      "slug": "svelte-ui-libraries",
      "description": "UI component libraries for Svelte",
      "resources": []
    },
    {
      "id": 24,
      "name": "React Native UI Libraries",
      "slug": "react-native-ui-libraries",
      "description": "UI component libraries for React Native mobile development",
      "resources": []
    },
    {
      "id": 25,
      "name": "Design Systems & Style Guides",
      "slug": "design-systems-style-guides",
      "description": "Design systems, style guides, and component documentation",
      "resources": []
    },
    {
      "id": 26,
      "name": "Online Design Tools",
      "slug": "online-design-tools",
      "description": "Web-based design tools and editors",
      "resources": []
    },
    {
      "id": 27,
      "name": "Downloadable Design Software",
      "slug": "downloadable-design-software",
      "description": "Desktop design applications and software",
      "resources": []
    },
    {
      "id": 28,
      "name": "Design Inspiration",
      "slug": "design-inspiration",
      "description": "Websites for design inspiration and references",
      "resources": []
    },
    {
      "id": 29,
      "name": "Image Compression",
      "slug": "image-compression",
      "description": "Tools and services for image optimization and compression",
      "resources": []
    },
    {
      "id": 30,
      "name": "Chrome Extensions",
      "slug": "chrome-extensions",
      "description": "Useful Chrome extensions for designers and developers",
      "resources": []
    },
    {
      "id": 31,
      "name": "Firefox Extensions",
      "slug": "firefox-extensions",
      "description": "Useful Firefox extensions for designers and developers",
      "resources": []
    },
    {
      "id": 32,
      "name": "AI Graphic Design Tools",
      "slug": "ai-graphic-design-tools",
      "description": "AI-powered tools for graphic design and image generation",
      "resources": []
    },
    {
      "id": 33,
      "name": "AI/ML Development Tools",
      "slug": "aiml-development-tools",
      "description": "Tools and platforms for AI/ML development and integration",
      "resources": []
    },
    {
      "id": 34,
      "name": "No-Code/Low-Code Platforms",
      "slug": "no-code-low-code-platforms",
      "description": "Visual development platforms requiring minimal coding",
      "resources": []
    },
    {
      "id": 35,
      "name": "Others",
      "slug": "others",
      "description": "Miscellaneous resources that don't fit other categories",
      "resources": []
    }
  ]
}
